pocketbase/__init__.py
pocketbase/pb.py
pocketbase/db/__init__.py
pocketbase/db/collection.py
pocketbase/deps/__init__.py
pocketbase/deps/auths.py
pocketpybase-0.1.9.5.dist-info/METADATA
pocketpybase-0.1.9.5.dist-info/WHEEL
pocketpybase-0.1.9.5.dist-info/top_level.txt
pocketpybase-0.1.9.5.dist-info/RECORD
