Metadata-Version: 2.1
Name: pocketpybase
Version: 0.1.9.5
Summary: A Python package for interacting with PocketBase
Author: Champ
Author-email: cs@two02.io
Requires-Dist: httpx
